qonic_misc/OperatorChecker.py
qonic_misc/RotationConversions.py
qonic_misc/__init__.py
qonic_misc-0.1.6.dist-info/METADATA
qonic_misc-0.1.6.dist-info/WHEEL
qonic_misc-0.1.6.dist-info/top_level.txt
qonic_misc-0.1.6.dist-info/RECORD
