Metadata-Version: 2.1
Name: qonic_misc
Version: 0.1.6
Summary: Python library with miscellaneous tools to be used in conjunction with the qonic framework
Home-page: https://github.com/Qonic-Team/qonic-misc.git
Download-URL: https://github.com/Qonic-Team/qonic-misc/archive/refs/heads/main.zip
Author: cogrpar
Author-email: owen.r.welsh@hotmail.com
License: Apache License 2.0
Keywords: qonic,qonic_misc
Requires-Dist: numpy >=1.22.2
Requires-Dist: tensorflow >=2.12.0rc1
Requires-Dist: keras >=2.13.1rc0
Requires-Dist: setuptools >=65.5.1
Requires-Dist: werkzeug >=3.0.3
Requires-Dist: wheel >=0.38.0
